{
  "produtos": [
    {
      "id": 1,
      "nome": "Teclado",
      "desc": "Teclado 102 Teclas - Mecânico.",
      "preco": 200,
      "img": "https://picsum.photos/100/100"
    },
    {
      "id": 2,
      "nome": "Mouse",
      "desc": "Mouse Gamer - 3200 DPI.",
      "preco": 100,
      "img": "https://picsum.photos/100/100"
    },
    {
      "id": 3,
      "nome": "Monitor",
      "desc": "Monitor 24' - 144Hz.",
      "preco": 800,
      "img": "https://picsum.photos/100/100"
    },
    {
      "id": 4,
      "nome": "Headset",
      "desc": "Headset Gamer - 7.1 Surround.",
      "preco": 300,
      "img": "https://picsum.photos/100/100"
    },
    {
      "id": 5,
      "nome": "Mousepad",
      "desc": "Mousepad Gamer - 80x30cm.",
      "preco": 50,
      "img": "https://picsum.photos/100/100"
    },
    {
      "id": 6,
      "nome": "Cadeira",
      "desc": "Cadeira Gamer - 180°.",
      "preco": 1000,
      "img": "https://picsum.photos/100/100"
    },
    {
      "id": 7,
      "nome": "Gabinete",
      "desc": "Gabinete Gamer - Vidro Temperado.",
      "preco": 500,
      "img": "https://picsum.photos/100/100"
    },
    {
      "id": 8,
      "nome": "Placa de Vídeo",
      "desc": "Placa de Vídeo - 8GB.",
      "preco": 2000,
      "img": "https://picsum.photos/100/100"
    },
    {
      "nome": "Pendrive",
      "desc": "16GB",
      "preco": "50",
      "img": "https://m.media-amazon.com/images/G/32/apparel/rcxgs/tile._CB483369971_.gif",
      "id": 9
    },
    {
      "nome": "Pendrive",
      "desc": "32GB",
      "preco": "78",
      "img": "https://m.media-amazon.com/images/G/32/apparel/rcxgs/tile._CB483369971_.gif",
      "id": 10
    },
    {
      "nome": "Pendrive",
      "desc": "64GB",
      "preco": "89",
      "img": "https://m.media-amazon.com/images/G/32/apparel/rcxgs/tile._CB483369971_.gif",
      "id": 11
    },
    {
      "nome": "Pendrive",
      "desc": "128Gb",
      "preco": "110",
      "img": "https://m.media-amazon.com/images/G/32/apparel/rcxgs/tile._CB483369971_.gif",
      "id": 12
    },
    {
      "id": 13,
      "nome": "Televisão",
      "desc": "14\"",
      "preco": "500",
      "img": "https://i.zst.com.br/thumbs/12/16/15/1005927.jpg/"
    }
  ]
}